sdrconnect/__init__.py
sdrconnect/clients/__init__.py
sdrconnect/clients/base.py
sdrconnect/clients/rtlsdr.py
sdrconnect/clients/spyserver.py
sdrconnect/core/__init__.py
sdrconnect/core/analysis.py
sdrconnect/core/config.py
sdrconnect/core/exceptions.py
sdrconnect-0.1.1.dist-info/METADATA
sdrconnect-0.1.1.dist-info/WHEEL
sdrconnect-0.1.1.dist-info/licenses/LICENSE
sdrconnect-0.1.1.dist-info/RECORD
