Metadata-Version: 2.4
Name: sdrconnect
Version: 0.1.1
Summary: Modern Python library for SDR connectivity and data collection
Project-URL: Homepage, https://github.com/isakruas/sdrconnect
Project-URL: Documentation, https://sdrconnect.readthedocs.io
Project-URL: Repository, https://github.com/isakruas/sdrconnect.git
Project-URL: Issues, https://github.com/isakruas/sdrconnect/issues
Author-email: Isak Ruas <isakruas@gmail.com>
Maintainer-email: Isak Ruas <isakruas@gmail.com>
License:                                  Apache License
License-File: LICENSE
Keywords: data-collection,radio,rtl-sdr,sdr,spyserver
Classifier: Development Status :: 3 - Alpha
Classifier: Intended Audience :: Developers
Classifier: Intended Audience :: Science/Research
Classifier: License :: OSI Approved :: Apache Software License
Classifier: Operating System :: OS Independent
Classifier: Programming Language :: Python :: 3
Classifier: Programming Language :: Python :: 3.8
Classifier: Programming Language :: Python :: 3.9
Classifier: Programming Language :: Python :: 3.10
Classifier: Programming Language :: Python :: 3.11
Classifier: Programming Language :: Python :: 3.12
Classifier: Topic :: Communications :: Ham Radio
Classifier: Topic :: Scientific/Engineering
Requires-Python: >=3.8
Requires-Dist: numpy>=1.20.0
Requires-Dist: scipy>=1.16.1
Provides-Extra: dev
Requires-Dist: black>=22.0.0; extra == 'dev'
Requires-Dist: flake8>=5.0.0; extra == 'dev'
Requires-Dist: isort>=5.10.0; extra == 'dev'
Requires-Dist: mypy>=1.0.0; extra == 'dev'
Requires-Dist: pytest-cov>=4.0.0; extra == 'dev'
Requires-Dist: pytest>=7.0.0; extra == 'dev'
Provides-Extra: docs
Requires-Dist: myst-parser>=0.18.0; extra == 'docs'
Requires-Dist: sphinx-rtd-theme>=1.0.0; extra == 'docs'
Requires-Dist: sphinx>=5.0.0; extra == 'docs'
Provides-Extra: viz
Requires-Dist: matplotlib>=3.5.0; extra == 'viz'
